scitopt/__init__.py
scitopt/core/__init__.py
scitopt/core/derivatives.py
scitopt/core/misc.py
scitopt/core/optimizers/__init__.py
scitopt/core/optimizers/common.py
scitopt/core/optimizers/linearlagrangian.py
scitopt/core/optimizers/loglagrangian.py
scitopt/core/optimizers/logmoc.py
scitopt/core/optimizers/oc.py
scitopt/core/projection.py
scitopt/core/visualization.py
scitopt/fea/__init__.py
scitopt/fea/composer.py
scitopt/fea/solver.py
scitopt/filter/__init__.py
scitopt/filter/helmholtz.py
scitopt/mesh/__init__.py
scitopt/mesh/loader.py
scitopt/mesh/task.py
scitopt/mesh/toy_problem.py
scitopt/mesh/utils.py
scitopt/mesh/visualization.py
scitopt/tools/__init__.py
scitopt/tools/history.py
scitopt/tools/logconf.py
scitopt/tools/scheduler.py
scitopt-0.1.6.dist-info/LICENSE
scitopt-0.1.6.dist-info/METADATA
scitopt-0.1.6.dist-info/WHEEL
scitopt-0.1.6.dist-info/RECORD
